rayai/__init__.py
rayai/base.py
rayai/batch.py
rayai/decorators.py
rayai/deployment.py
rayai/resource_loader.py
rayai/utils.py
rayai/adapters/__init__.py
rayai/adapters/abc.py
rayai/adapters/core.py
rayai/adapters/langchain/__init__.py
rayai/adapters/langchain/tools.py
rayai/adapters/pydantic/__init__.py
rayai/adapters/pydantic/tools.py
rayai/cli/__init__.py
rayai/cli/analytics.py
rayai/cli/cli.py
rayai/cli/commands/__init__.py
rayai/cli/commands/analytics.py
rayai/cli/commands/create_agent.py
rayai/cli/commands/init.py
rayai/cli/commands/serve.py
rayai/cli/templates/__init__.py
rayai/cli/templates/agent/README.md
rayai/cli/templates/agent/__init__.py
rayai/cli/templates/agent/pyproject.toml
rayai/cli/templates/agent/agents/.gitkeep
rayai/examples/__init__.py
rayai/sandbox/__init__.py
rayai/sandbox/config.py
rayai/sandbox/executor.py
rayai/sandbox/mcp_proxy.py
rayai/sandbox/tools.py
rayai/sandbox/types.py
rayai-0.1.1.dist-info/licenses/LICENSE
rayai-0.1.1.dist-info/METADATA
rayai-0.1.1.dist-info/WHEEL
rayai-0.1.1.dist-info/entry_points.txt
rayai-0.1.1.dist-info/top_level.txt
rayai-0.1.1.dist-info/RECORD
