Metadata-Version: 2.4
Name: rayai
Version: 0.1.1
Summary: Run agentic workloads on Ray
License:                                  Apache License
Project-URL: Homepage, https://rayai.com
Project-URL: Repository, https://github.com/rayai-labs/agentic-ray
Keywords: ray,agents,ai,llm,distributed,pydantic-ai,langchain,parallel tool call
Requires-Python: >=3.12
License-File: LICENSE
Requires-Dist: langchain>=1.0.0
Requires-Dist: langchain-openai>=0.3.35
Requires-Dist: langgraph>=0.6.10
Requires-Dist: ray[serve]>=2.49.2
Requires-Dist: openai>=1.0.0
Requires-Dist: python-dotenv>=1.0.0
Requires-Dist: fastapi>=0.100.0
Requires-Dist: click>=8.0.0
Requires-Dist: pydantic-ai-slim[openai]>=1.27.0
Requires-Dist: posthog>=3.0.0
Provides-Extra: sandbox
Requires-Dist: docker>=7.0.0; extra == "sandbox"
Requires-Dist: requests>=2.31.0; extra == "sandbox"
Dynamic: license-file
